<entry>
    <version>7.6</version>
    <ios_version>1</ios_version>
    <url>https://ssanfrancisco.kapeli.com/feeds/TYPO3.tgz</url>
    <url>https://slondon.kapeli.com/feeds/TYPO3.tgz</url>
    <url>https://snewyork.kapeli.com/feeds/TYPO3.tgz</url>
    <url>https://stokyo.kapeli.com/feeds/TYPO3.tgz</url>
    <url>https://sfrankfurt.kapeli.com/feeds/TYPO3.tgz</url>
    <url>https://ssingapore.kapeli.com/feeds/TYPO3.tgz</url>
    <other-versions>
        <version><name>7.6</name></version>
        <version><name>6.2</name></version>
        <version><name>6.1</name></version>
        <version><name>6.0</name></version>
        <version><name>4.7</name></version>
        <version><name>4.6</name></version>
        <version><name>4.5</name></version>
    </other-versions>
</entry>